invoicex/__init__.py
invoicex/invoicex.py
invoicex/populate.py
invoicex/facturx/__init__.py
invoicex/facturx/_version.py
invoicex/facturx/facturx.py
invoicex/facturx/logger.py
invoicex/facturx/pdfwriter.py
invoicex/facturx/flavors/__init__.py
invoicex/facturx/flavors/fields.yml
invoicex/facturx/flavors/flavors.yml
invoicex/facturx/flavors/xml_flavor.py
invoicex/facturx/flavors/factur-x/xml/basic.xml
invoicex/facturx/flavors/factur-x/xml/basicwl.xml
invoicex/facturx/flavors/factur-x/xml/en16931.xml
invoicex/facturx/flavors/factur-x/xml/minimum.xml
invoicex/facturx/flavors/factur-x/xmp/Factur-X_extension_schema.xmp
invoicex/facturx/flavors/factur-x/xsd/FACTUR-X_BASIC-WL.xsd
invoicex/facturx/flavors/factur-x/xsd/FACTUR-X_BASIC-WL_urn_un_unece_uncefact_data_standard_QualifiedDataType_100.xsd
invoicex/facturx/flavors/factur-x/xsd/FACTUR-X_BASIC-WL_urn_un_unece_uncefact_data_standard_ReusableAggregateBusinessInformationEntity_100.xsd
invoicex/facturx/flavors/factur-x/xsd/FACTUR-X_BASIC-WL_urn_un_unece_uncefact_data_standard_UnqualifiedDataType_100.xsd
invoicex/facturx/flavors/factur-x/xsd/FACTUR-X_EN16931.xsd
invoicex/facturx/flavors/factur-x/xsd/FACTUR-X_EN16931_urn_un_unece_uncefact_data_standard_QualifiedDataType_100.xsd
invoicex/facturx/flavors/factur-x/xsd/FACTUR-X_EN16931_urn_un_unece_uncefact_data_standard_ReusableAggregateBusinessInformationEntity_100.xsd
invoicex/facturx/flavors/factur-x/xsd/FACTUR-X_EN16931_urn_un_unece_uncefact_data_standard_UnqualifiedDataType_100.xsd
invoicex/facturx/flavors/zugferd/xml/basic.xml
invoicex/facturx/flavors/zugferd/xml/comfort.xml
invoicex/facturx/flavors/zugferd/xmp/ZUGFeRD_extension_schema.xmp
invoicex/facturx/flavors/zugferd/xsd/ZUGFeRD1p0.xsd
invoicex/facturx/flavors/zugferd/xsd/ZUGFeRD1p0_urn_un_unece_uncefact_data_standard_QualifiedDataType_12.xsd
invoicex/facturx/flavors/zugferd/xsd/ZUGFeRD1p0_urn_un_unece_uncefact_data_standard_ReusableAggregateBusinessInformationEntity_12.xsd
invoicex_gui-0.1.1.dist-info/LICENSE
invoicex_gui-0.1.1.dist-info/METADATA
invoicex_gui-0.1.1.dist-info/WHEEL
invoicex_gui-0.1.1.dist-info/entry_points.txt
invoicex_gui-0.1.1.dist-info/top_level.txt
invoicex_gui-0.1.1.dist-info/RECORD
