Metadata-Version: 2.1
Name: invoicex-gui
Version: 0.1.1
Summary: Graphical User Interface for factur-x library with basic functionalities
Home-page: https://github.com/invoice-x/invoicex-gui
Author: Harshit Joshi
Author-email: harshit.joshi@outlook.com
License: GNU General Public License (GPL)
Platform: UNKNOWN
Requires-Dist: PyQt5 (==5.10.1)
Requires-Dist: PyPDF2
Requires-Dist: lxml
Requires-Dist: PyYAML
Requires-Dist: invoice2data
